{
  "generatedAt": "2026-04-07T00:00:00.000Z",
  "plugins": [
    {
      "pluginId": "photochemist",
      "displayName": "PhotoChemist",
      "manifestUrl": "https://dec18studios.github.io/Dec18-Plugin-Manager/plugins/photochemist/stable.json"
    },
    {
      "pluginId": "resolve-node-toggler",
      "displayName": "Resolve Node Toggler",
      "manifestUrl": "https://dec18studios.github.io/Dec18-Plugin-Manager/plugins/resolve-node-toggler/stable.json"
    },
    {
      "pluginId": "rgb-chips-dctl",
      "displayName": "RGB Chips",
      "licenseTier": "free",
      "manifestUrl": "https://dec18studios.github.io/Dec18-Plugin-Manager/plugins/rgb-chips-dctl/stable.json"
    }
  ]
}
